<?xml version = '1.0' encoding = 'UTF-8'?>
<Diagram class="oracle.dbtools.crest.swingui.relational.DPVRelational" name="Relational_1" id="46C3B770-8AA5-FDC7-B90E-72EF22364003">
<createdBy>root</createdBy>
<modifiedBy>root</modifiedBy>
<createdTime>2018-04-10 20:47:41 UTC</createdTime>
<autoRoute>false</autoRoute>
<boxInbox>true</boxInbox>
<showLegend>false</showLegend>
<showLabels>false</showLabels>
<showRelAttributes>false</showRelAttributes>
<gridEnabled>false</gridEnabled>
<showGrid>false</showGrid>
<diagramColor>-1</diagramColor>
<display>false</display>
<notation>0</notation>
<objectViews>
<OView class="oracle.dbtools.crest.swingui.relational.TVTable" oid="082A5CAC-7F86-F705-662A-A79277ACC79E" otype="Table" vid="4FA35A02-FFBA-ABDB-7960-991A209252E3">
<hideElementsInCurrentOnly>false</hideElementsInCurrentOnly>
<bounds x="20" y="1496" width="179" height="70"/>
</OView>
<OView class="oracle.dbtools.crest.swingui.relational.TVTable" oid="22559CD3-AC25-A476-2BF3-01DF9F0B022B" otype="Table" vid="12E0786D-C2D6-CAC1-3253-FDA0778A2F08">
<hideElementsInCurrentOnly>false</hideElementsInCurrentOnly>
<bounds x="1532" y="474" width="196" height="174"/>
</OView>
<OView class="oracle.dbtools.crest.swingui.relational.TVTable" oid="22741908-4809-D600-5A09-E1D73EBD8D50" otype="Table" vid="C88D4C65-74BD-6D28-0719-22A0DE1B2100">
<hideElementsInCurrentOnly>false</hideElementsInCurrentOnly>
<bounds x="691" y="1496" width="160" height="70"/>
</OView>
<OView class="oracle.dbtools.crest.swingui.relational.TVTable" oid="27F5497C-CBBE-27D2-32F8-36707941BFE5" otype="Table" vid="B7E6DA35-2F6F-DD44-9012-FBAAFAB77162">
<hideElementsInCurrentOnly>false</hideElementsInCurrentOnly>
<bounds x="249" y="1496" width="157" height="83"/>
</OView>
<OView class="oracle.dbtools.crest.swingui.relational.TVTable" oid="32B43389-F2C3-729E-1292-F504144BA1E7" otype="Table" vid="7B0B1BB2-8826-43BE-4BC2-3A04EF7A2B2E">
<hideElementsInCurrentOnly>false</hideElementsInCurrentOnly>
<bounds x="892" y="311" width="201" height="96"/>
</OView>
<OView class="oracle.dbtools.crest.swingui.relational.TVTable" oid="34150080-E7DB-1729-788F-F5001DA439F0" otype="Table" vid="2D13F5A8-4012-8CDC-8087-C2DF67D32814">
<hideElementsInCurrentOnly>false</hideElementsInCurrentOnly>
<bounds x="249" y="1729" width="188" height="96"/>
</OView>
<OView class="oracle.dbtools.crest.swingui.relational.TVTable" oid="3DEB53AD-F11A-74F4-5F10-8C411C8B1363" otype="Table" vid="842A1E74-1610-4E84-45CC-69DB654F3770">
<hideElementsInCurrentOnly>false</hideElementsInCurrentOnly>
<bounds x="289" y="675" width="189" height="206"/>
</OView>
<OView class="oracle.dbtools.crest.swingui.relational.TVTable" oid="3EF833EE-B61F-ECE0-3210-21C51FE12611" otype="Table" vid="0F805848-3AF1-3C6E-B7C2-B094F6C1C990">
<hideElementsInCurrentOnly>false</hideElementsInCurrentOnly>
<bounds x="568" y="623" width="187" height="83"/>
</OView>
<OView class="oracle.dbtools.crest.swingui.relational.TVTable" oid="64F504F7-9F3C-AA72-D7D5-1CAC590C8043" otype="Table" vid="85553454-D266-65E3-71F7-4C7F31C060B5">
<hideElementsInCurrentOnly>false</hideElementsInCurrentOnly>
<bounds x="543" y="1233" width="184" height="83"/>
</OView>
<OView class="oracle.dbtools.crest.swingui.relational.TVTable" oid="65EBC780-3418-60B6-F2BD-930F483F4347" otype="Table" vid="2E429DB6-A6FD-92A0-F7F1-81A07C3B1D3E">
<hideElementsInCurrentOnly>false</hideElementsInCurrentOnly>
<bounds x="20" y="675" width="188" height="141"/>
</OView>
<OView class="oracle.dbtools.crest.swingui.relational.TVTable" oid="82927B12-DF65-7E6C-0C3F-CA88EAB4A9FC" otype="Table" vid="0AD0BDC7-2747-135B-4A92-ADB0F17DE244">
<hideElementsInCurrentOnly>false</hideElementsInCurrentOnly>
<bounds x="551" y="20" width="220" height="141"/>
</OView>
<OView class="oracle.dbtools.crest.swingui.relational.TVTable" oid="8447EE83-55DC-7CEB-7E3D-FF2017F995F3" otype="Table" vid="ACA8B0F3-DDF7-67D7-1623-26015CC21216">
<hideElementsInCurrentOnly>false</hideElementsInCurrentOnly>
<bounds x="20" y="876" width="188" height="83"/>
</OView>
<OView class="oracle.dbtools.crest.swingui.relational.TVTable" oid="87604299-484F-CEA9-C0D3-0B11041A68D8" otype="Table" vid="24827602-3716-5983-7374-D4EE2E0A81FA">
<hideElementsInCurrentOnly>false</hideElementsInCurrentOnly>
<bounds x="1264" y="474" width="188" height="148"/>
</OView>
<OView class="oracle.dbtools.crest.swingui.relational.TVTable" oid="A8A3D136-5121-AAB3-FDD3-41DDC4B54DCA" otype="Table" vid="DCA84B2D-681E-E906-87DD-2572BC9DE290">
<hideElementsInCurrentOnly>false</hideElementsInCurrentOnly>
<bounds x="289" y="941" width="174" height="83"/>
</OView>
<OView class="oracle.dbtools.crest.swingui.relational.TVTable" oid="A8F36E6D-5796-F1C7-9C79-E9313652F2DE" otype="Table" vid="5CB46FB7-7CCF-3170-140D-22252353538E">
<hideElementsInCurrentOnly>false</hideElementsInCurrentOnly>
<bounds x="892" y="221" width="191" height="70"/>
</OView>
<OView class="oracle.dbtools.crest.swingui.relational.TVTable" oid="BAA777D0-E330-543A-0D74-B143A02B9BAC" otype="Table" vid="0BEE36A5-65F0-13B2-E1FB-5F764957EEC4">
<hideElementsInCurrentOnly>false</hideElementsInCurrentOnly>
<bounds x="551" y="221" width="261" height="193"/>
</OView>
<OView class="oracle.dbtools.crest.swingui.relational.TVTable" oid="DAB461BD-C71A-6F7E-52CB-719FCFD0CA26" otype="Table" vid="7676E2B6-0AF7-D1DF-B746-295A3D150B6A">
<hideElementsInCurrentOnly>false</hideElementsInCurrentOnly>
<bounds x="543" y="941" width="190" height="232"/>
</OView>
<OView class="oracle.dbtools.crest.swingui.relational.TVTable" oid="E1B9336B-1D41-5C41-2C08-BE680A69979F" otype="Table" vid="38E0CC21-24E7-4D19-BB57-047B10E04281">
<hideElementsInCurrentOnly>false</hideElementsInCurrentOnly>
<bounds x="456" y="1496" width="185" height="83"/>
</OView>
<OView class="oracle.dbtools.crest.swingui.relational.TVTable" oid="E48675CB-2A46-0D58-595A-C0BC12623631" otype="Table" vid="C4BD03F8-1840-546E-A899-01823DEFF0AA">
<hideElementsInCurrentOnly>false</hideElementsInCurrentOnly>
<bounds x="288" y="474" width="183" height="141"/>
</OView>
<OView class="oracle.dbtools.crest.swingui.relational.TVTable" oid="E4A16B00-CD99-E9BE-C51B-93C445F55577" otype="Table" vid="31C85BEB-B76C-EEBA-FC97-8F7EF5AA92B4">
<hideElementsInCurrentOnly>false</hideElementsInCurrentOnly>
<bounds x="569" y="815" width="168" height="83"/>
</OView>
<OView class="oracle.dbtools.crest.swingui.relational.TVTable" oid="E89BB779-12D4-E87A-6A73-DE777E8FF08D" otype="Table" vid="D8D0944E-B2C1-7104-432F-77E0C8D588F6">
<hideElementsInCurrentOnly>false</hideElementsInCurrentOnly>
<bounds x="20" y="1729" width="179" height="70"/>
</OView>
<OView class="oracle.dbtools.crest.swingui.relational.TVTable" oid="EEFCE2BE-B07B-6D17-7675-1153407A50D2" otype="Table" vid="628AFF84-DC39-50EC-4885-1E2BAA0EC990">
<hideElementsInCurrentOnly>false</hideElementsInCurrentOnly>
<bounds x="813" y="941" width="184" height="70"/>
</OView>
<OView class="oracle.dbtools.crest.swingui.relational.TVTable" oid="F1107E19-0BCD-58FC-CF40-0549A7CA1FE3" otype="Table" vid="69AF54A9-5BC6-C8D5-D1D8-37A7F71BAFBB">
<hideElementsInCurrentOnly>false</hideElementsInCurrentOnly>
<bounds x="851" y="20" width="179" height="70"/>
</OView>
<OView class="oracle.dbtools.crest.swingui.relational.TVTable" oid="FD9F57D3-ED6A-15CD-2EA3-B9FF266A5F91" otype="Table" vid="7D44333A-F9D7-D8BB-E554-0DD299197586">
<hideElementsInCurrentOnly>false</hideElementsInCurrentOnly>
<bounds x="568" y="730" width="207" height="70"/>
</OView>
</objectViews>
<connectors>
<Connector class="oracle.dbtools.crest.swingui.relational.TVFKRelation" oid="0C079453-0867-F290-4A9E-1F5F9B2E137A" otype="FKIndexAssociation" vid_source="69AF54A9-5BC6-C8D5-D1D8-37A7F71BAFBB" vid_target="0AD0BDC7-2747-135B-4A92-ADB0F17DE244">
<hideElementsInCurrentOnly>false</hideElementsInCurrentOnly>
<lineWidth>1</lineWidth>
<points>
<point x="851" y="55"/>
<point x="771" y="55"/>
</points>
</Connector>
<Connector class="oracle.dbtools.crest.swingui.relational.TVFKRelation" oid="159862BC-0150-767B-F9EC-D41DCBEB197F" otype="FKIndexAssociation" vid_source="C4BD03F8-1840-546E-A899-01823DEFF0AA" vid_target="2E429DB6-A6FD-92A0-F7F1-81A07C3B1D3E">
<hideElementsInCurrentOnly>false</hideElementsInCurrentOnly>
<lineWidth>1</lineWidth>
<points>
<point x="288" y="613"/>
<point x="207" y="675"/>
</points>
</Connector>
<Connector class="oracle.dbtools.crest.swingui.relational.TVFKRelation" oid="176D5721-23CA-0433-27CE-0AF260A16F8C" otype="FKIndexAssociation" vid_source="0BEE36A5-65F0-13B2-E1FB-5F764957EEC4" vid_target="0AD0BDC7-2747-135B-4A92-ADB0F17DE244">
<hideElementsInCurrentOnly>false</hideElementsInCurrentOnly>
<lineWidth>1</lineWidth>
<points>
<point x="661" y="221"/>
<point x="661" y="161"/>
</points>
</Connector>
<Connector class="oracle.dbtools.crest.swingui.relational.TVFKRelation" oid="1F8E0303-B017-E2B6-B997-DF03E5806E86" otype="FKIndexAssociation" vid_source="628AFF84-DC39-50EC-4885-1E2BAA0EC990" vid_target="7676E2B6-0AF7-D1DF-B746-295A3D150B6A">
<hideElementsInCurrentOnly>false</hideElementsInCurrentOnly>
<lineWidth>1</lineWidth>
<points>
<point x="813" y="976"/>
<point x="733" y="976"/>
</points>
</Connector>
<Connector class="oracle.dbtools.crest.swingui.relational.TVFKRelation" oid="2FC18123-7211-AA16-26B8-1F20BB576A6E" otype="FKIndexAssociation" vid_source="DCA84B2D-681E-E906-87DD-2572BC9DE290" vid_target="ACA8B0F3-DDF7-67D7-1623-26015CC21216">
<hideElementsInCurrentOnly>false</hideElementsInCurrentOnly>
<lineWidth>1</lineWidth>
<points>
<point x="289" y="950"/>
<point x="208" y="950"/>
</points>
</Connector>
<Connector class="oracle.dbtools.crest.swingui.relational.TVFKRelation" oid="42F78623-25D0-5359-8909-F095B731744F" otype="FKIndexAssociation" vid_source="5CB46FB7-7CCF-3170-140D-22252353538E" vid_target="0BEE36A5-65F0-13B2-E1FB-5F764957EEC4">
<hideElementsInCurrentOnly>false</hideElementsInCurrentOnly>
<lineWidth>1</lineWidth>
<points>
<point x="892" y="256"/>
<point x="812" y="256"/>
</points>
</Connector>
<Connector class="oracle.dbtools.crest.swingui.relational.TVFKRelation" oid="497341BD-DD85-3E1A-C52E-D93B82AD1B84" otype="FKIndexAssociation" vid_source="85553454-D266-65E3-71F7-4C7F31C060B5" vid_target="7676E2B6-0AF7-D1DF-B746-295A3D150B6A">
<hideElementsInCurrentOnly>false</hideElementsInCurrentOnly>
<lineWidth>1</lineWidth>
<points>
<point x="635" y="1233"/>
<point x="635" y="1173"/>
</points>
</Connector>
<Connector class="oracle.dbtools.crest.swingui.relational.TVFKRelation" oid="4DA53629-1E20-D932-E6E5-B6C7FB50B135" otype="FKIndexAssociation" vid_source="0BEE36A5-65F0-13B2-E1FB-5F764957EEC4" vid_target="C4BD03F8-1840-546E-A899-01823DEFF0AA">
<hideElementsInCurrentOnly>false</hideElementsInCurrentOnly>
<lineWidth>1</lineWidth>
<points>
<point x="553" y="414"/>
<point x="471" y="475"/>
</points>
</Connector>
<Connector class="oracle.dbtools.crest.swingui.relational.TVFKRelation" oid="63CAA223-65AF-2B51-EC33-F9F31774C9EE" otype="FKIndexAssociation" vid_source="7676E2B6-0AF7-D1DF-B746-295A3D150B6A" vid_target="842A1E74-1610-4E84-45CC-69DB654F3770">
<hideElementsInCurrentOnly>false</hideElementsInCurrentOnly>
<lineWidth>1</lineWidth>
<points>
<point x="543" y="952"/>
<point x="477" y="881"/>
</points>
</Connector>
<Connector class="oracle.dbtools.crest.swingui.relational.TVFKRelation" oid="70FE260E-8117-57A2-EB82-6448364EFD35" otype="FKIndexAssociation" vid_source="31C85BEB-B76C-EEBA-FC97-8F7EF5AA92B4" vid_target="842A1E74-1610-4E84-45CC-69DB654F3770">
<hideElementsInCurrentOnly>false</hideElementsInCurrentOnly>
<lineWidth>1</lineWidth>
<points>
<point x="569" y="848"/>
<point x="478" y="848"/>
</points>
</Connector>
<Connector class="oracle.dbtools.crest.swingui.relational.TVFKRelation" oid="79AF96EB-3533-FB2C-86E0-F16C541F39FD" otype="FKIndexAssociation" vid_source="DCA84B2D-681E-E906-87DD-2572BC9DE290" vid_target="842A1E74-1610-4E84-45CC-69DB654F3770">
<hideElementsInCurrentOnly>false</hideElementsInCurrentOnly>
<lineWidth>1</lineWidth>
<points>
<point x="376" y="941"/>
<point x="376" y="881"/>
</points>
</Connector>
<Connector class="oracle.dbtools.crest.swingui.relational.TVFKRelation" oid="951A3BD4-A24A-87F1-8E24-367DFBC67C9D" otype="FKIndexAssociation" vid_source="12E0786D-C2D6-CAC1-3253-FDA0778A2F08" vid_target="0BEE36A5-65F0-13B2-E1FB-5F764957EEC4">
<hideElementsInCurrentOnly>false</hideElementsInCurrentOnly>
<lineWidth>1</lineWidth>
<points>
<point x="1532" y="535"/>
<point x="812" y="351"/>
</points>
</Connector>
<Connector class="oracle.dbtools.crest.swingui.relational.TVFKRelation" oid="A35B283D-F51F-40BD-F6D6-5F74DFD26DE7" otype="FKIndexAssociation" vid_source="7B0B1BB2-8826-43BE-4BC2-3A04EF7A2B2E" vid_target="0BEE36A5-65F0-13B2-E1FB-5F764957EEC4">
<hideElementsInCurrentOnly>false</hideElementsInCurrentOnly>
<lineWidth>1</lineWidth>
<points>
<point x="892" y="379"/>
<point x="812" y="379"/>
</points>
</Connector>
<Connector class="oracle.dbtools.crest.swingui.relational.TVFKRelation" oid="AB7D2E15-CCDD-A4E4-C904-D3F76D0E0809" otype="FKIndexAssociation" vid_source="2E429DB6-A6FD-92A0-F7F1-81A07C3B1D3E" vid_target="ACA8B0F3-DDF7-67D7-1623-26015CC21216">
<hideElementsInCurrentOnly>false</hideElementsInCurrentOnly>
<lineWidth>1</lineWidth>
<points>
<point x="114" y="816"/>
<point x="114" y="876"/>
</points>
</Connector>
<Connector class="oracle.dbtools.crest.swingui.relational.TVFKRelation" oid="B7AA14C3-FA75-1675-75DB-0AB00D95B464" otype="FKIndexAssociation" vid_source="24827602-3716-5983-7374-D4EE2E0A81FA" vid_target="0BEE36A5-65F0-13B2-E1FB-5F764957EEC4">
<hideElementsInCurrentOnly>false</hideElementsInCurrentOnly>
<lineWidth>1</lineWidth>
<points>
<point x="1264" y="515"/>
<point x="812" y="361"/>
</points>
</Connector>
<Connector class="oracle.dbtools.crest.swingui.relational.TVFKRelation" oid="BE7F0BFC-C996-669C-2420-722536BC0AF5" otype="FKIndexAssociation" vid_source="842A1E74-1610-4E84-45CC-69DB654F3770" vid_target="C4BD03F8-1840-546E-A899-01823DEFF0AA">
<hideElementsInCurrentOnly>false</hideElementsInCurrentOnly>
<lineWidth>1</lineWidth>
<points>
<point x="380" y="675"/>
<point x="380" y="615"/>
</points>
</Connector>
<Connector class="oracle.dbtools.crest.swingui.relational.TVFKRelation" oid="CDDA2074-55A1-FD20-8901-B10390B5B4F6" otype="FKIndexAssociation" vid_source="0F805848-3AF1-3C6E-B7C2-B094F6C1C990" vid_target="842A1E74-1610-4E84-45CC-69DB654F3770">
<hideElementsInCurrentOnly>false</hideElementsInCurrentOnly>
<lineWidth>1</lineWidth>
<points>
<point x="568" y="690"/>
<point x="478" y="690"/>
</points>
</Connector>
<Connector class="oracle.dbtools.crest.swingui.relational.TVFKRelation" oid="D6F1017F-77F0-A2F3-2666-9DE2EAC18401" otype="FKIndexAssociation" vid_source="7D44333A-F9D7-D8BB-E554-0DD299197586" vid_target="842A1E74-1610-4E84-45CC-69DB654F3770">
<hideElementsInCurrentOnly>false</hideElementsInCurrentOnly>
<lineWidth>1</lineWidth>
<points>
<point x="568" y="765"/>
<point x="478" y="765"/>
</points>
</Connector>
</connectors>
</Diagram>